adder.t.v
// Adder testbench
`timescale 1 ns / 1 ps
`include "adder.v"

module testFullAdder();
    reg a, b, carryin;
    wire sum, carryout;

    //behavioralFullAdder adder (sum, carryout, a, b, carryin);
    structuralFullAdder adder (sum, carryout, a, b, carryin);

    initial begin
        // Your test code here

        $dumpfile("adder-dump.vcd");
        $dumpvars();
	
	$display("A B Cin | Sum Cout");
	a=0;b=0;carryin=0; #1000
	$display("%b %b %b   |  %b %b", a, b, carryin, sum, carryout);
	a=0;b=0;carryin=1; #1000
	$display("%b %b %b   |  %b %b", a, b, carryin, sum, carryout);
	a=0;b=1;carryin=0; #1000
	$display("%b %b %b   |  %b %b", a, b, carryin, sum, carryout);
	a=0;b=1;carryin=1; #1000
	$display("%b %b %b   |  %b %b", a, b, carryin, sum, carryout);
	a=1;b=0;carryin=0; #1000
	$display("%b %b %b   |  %b %b", a, b, carryin, sum, carryout);
	a=1;b=0;carryin=1; #1000
	$display("%b %b %b   |  %b %b", a, b, carryin, sum, carryout);
	a=1;b=1;carryin=0; #1000
	$display("%b %b %b   |  %b %b", a, b, carryin, sum, carryout);
	a=1;b=1;carryin=1; #1000
	$display("%b %b %b   |  %b %b", a, b, carryin, sum, carryout);
    end
endmodule

//    //structuralDecoder decoder (out0,out1,out2,out3,addr0,addr1,enable); // Swap after testing
//
//    initial begin
//    $display("En A0 A1| O0 O1 O2 O3 | Expected Output");
//    enable=0;addr0=0;addr1=0; #1000 
//    $display("%b  %b  %b |  %b  %b  %b  %b | All false", enable, addr0, addr1, out0, out1, out2, out3);
//    enable=0;addr0=1;addr1=0; #1000
//    $display("%b  %b  %b |  %b  %b  %b  %b | All false", enable, addr0, addr1, out0, out1, out2, out3);
//    enable=0;addr0=0;addr1=1; #1000 
//    $display("%b  %b  %b |  %b  %b  %b  %b | All false", enable, addr0, addr1, out0, out1, out2, out3);
//    enable=0;addr0=1;addr1=1; #1000 
//    $display("%b  %b  %b |  %b  %b  %b  %b | All false", enable, addr0, addr1, out0, out1, out2, out3);
//    enable=1;addr0=0;addr1=0; #1000 
//    $display("%b  %b  %b |  %b  %b  %b  %b | O0 Only", enable, addr0, addr1, out0, out1, out2, out3);
//    enable=1;addr0=1;addr1=0; #1000 
//    $display("%b  %b  %b |  %b  %b  %b  %b | O1 Only", enable, addr0, addr1, out0, out1, out2, out3);
//    enable=1;addr0=0;addr1=1; #1000 
//    $display("%b  %b  %b |  %b  %b  %b  %b | O2 Only", enable, addr0, addr1, out0, out1, out2, out3);
//    enable=1;addr0=1;addr1=1; #1000 
//    $display("%b  %b  %b |  %b  %b  %b  %b | O3 Only", enable, addr0, addr1, out0, out1, out2, out3);

adder.v
// Adder circuit
`define AND and #50
`define OR or #50
`define XOR xor #50
`define NOT not #50

module behavioralFullAdder
(
    output sum, 
    output carryout,
    input a, 
    input b, 
    input carryin
);
    // Uses concatenation operator and built-in '+'
    assign {carryout, sum}=a+b+carryin;
endmodule

module structuralFullAdder
(
    output sum, 
    output carryout,
    input a, 
    input b, 
    input carryin
);
    // Your adder code here
    wire AxorB;
    wire AandB;
    wire AandC;
    wire BandC;

    xor xorgate(AxorB, a, b);
    xor xorgate(sum, AxorB, carryin);
    and andgate(AandB, a, b);
    and andgate(AandC, a, carryin);
    and andgate(BandC, b, carryin);
    or orgate(carryout, AandB, AandC, BandC);
endmodule

adder-dump.vcd
$date
	Fri Sep 21 13:44:57 2018
$end
$version
	Icarus Verilog
$end
$timescale
	1ps
$end
$scope module behavioralFullAdder $end
$var wire 1 ! a $end
$var wire 1 " b $end
$var wire 1 # carryin $end
$var wire 1 $ carryout $end
$var wire 1 % sum $end
$upscope $end
$scope module testFullAdder $end
$var wire 1 & carryout $end
$var wire 1 ' sum $end
$var reg 1 ( a $end
$var reg 1 ) b $end
$var reg 1 * carryin $end
$scope module adder $end
$var wire 1 + AandB $end
$var wire 1 , AandC $end
$var wire 1 - AxorB $end
$var wire 1 . BandC $end
$var wire 1 / a $end
$var wire 1 0 b $end
$var wire 1 1 carryin $end
$var wire 1 & carryout $end
$var wire 1 ' sum $end
$upscope $end
$upscope $end
$enddefinitions $end
#0
$dumpvars
01
00
0/
0.
0-
0,
0+
0*
0)
0(
0'
0&
x%
x$
z#
z"
z!
$end
#1000000
1'
1*
11
#2000000
1-
0*
01
1)
10
#3000000
1&
0'
1.
1*
11
#4000000
0&
1'
0.
0*
01
0)
00
1(
1/
#5000000
1&
0'
1,
1*
11
#6000000
0,
0-
1+
0*
01
1)
10
#7000000
1'
1,
1.
1*
11
