decoder.t.v
// Decoder testbench
`timescale 1 ns / 1 ps
`include "decoder.v"

module testDecoder (); 
    reg addr0, addr1;
    reg enable;
    wire out0,out1,out2,out3;

    //behavioralDecoder decoder (out0,out1,out2,out3,addr0,addr1,enable);
    structuralDecoder decoder (out0,out1,out2,out3,addr0,addr1,enable); // Swap after testing

    initial begin

    $display("En A0 A1| O0 O1 O2 O3 | Expected Output");
    $dumpfile("decoder-dump.vcd");

    $dumpvars();
    enable=0;addr0=0;addr1=0; #1000 
    $display("%b  %b  %b |  %b  %b  %b  %b | All false", enable, addr0, addr1, out0, out1, out2, out3);
    enable=0;addr0=1;addr1=0; #1000
    $display("%b  %b  %b |  %b  %b  %b  %b | All false", enable, addr0, addr1, out0, out1, out2, out3);
    enable=0;addr0=0;addr1=1; #1000 
    $display("%b  %b  %b |  %b  %b  %b  %b | All false", enable, addr0, addr1, out0, out1, out2, out3);
    enable=0;addr0=1;addr1=1; #1000 
    $display("%b  %b  %b |  %b  %b  %b  %b | All false", enable, addr0, addr1, out0, out1, out2, out3);
    enable=1;addr0=0;addr1=0; #1000 
    $display("%b  %b  %b |  %b  %b  %b  %b | O0 Only", enable, addr0, addr1, out0, out1, out2, out3);
    enable=1;addr0=1;addr1=0; #1000 
    $display("%b  %b  %b |  %b  %b  %b  %b | O1 Only", enable, addr0, addr1, out0, out1, out2, out3);
    enable=1;addr0=0;addr1=1; #1000 
    $display("%b  %b  %b |  %b  %b  %b  %b | O2 Only", enable, addr0, addr1, out0, out1, out2, out3);
    enable=1;addr0=1;addr1=1; #1000 
    $display("%b  %b  %b |  %b  %b  %b  %b | O3 Only", enable, addr0, addr1, out0, out1, out2, out3);
    end

endmodule

decoder.v
// Decoder circuit
`define AND and #50
`define OR or #50
`define XOR xor #50
`define NOT not #50

module behavioralDecoder
(
    output out0, out1, out2, out3,
    input address0, address1,
    input enable
);
    // Uses concatenation and shift operators
    assign {out3,out2,out1,out0}=enable<<{address1,address0};
endmodule


module structuralDecoder
(
    output out0, out1, out2, out3,
    input address0, address1,
    input enable
);
    // Your decoder code here
    wire nA0;
    wire nA1;
    wire nA0andnA1;
    wire nA0andA1;
    wire A0andnA1;
    wire A0andA1;
    
    `NOT A0inv(nA0, address0);
    `NOT A1inv(nA1, address1);
    `AND andgate(nA0andnA1, nA0, nA1);
    `AND andgate(nA0andA1, nA0, address1);
    `AND andgate(A0andnA1, address0, nA1);
    `AND andgate(A0andA1, address0, address1);

    `AND andgate(out0, nA0andnA1, enable);
    `AND andgate(out1, A0andnA1, enable);
    `AND andgate(out2, nA0andA1, enable);
    `AND andgate(out3, A0andA1, enable);
endmodule

decoder-dump.vcd
$date
	Fri Sep 21 13:48:56 2018
$end
$version
	Icarus Verilog
$end
$timescale
	1ps
$end
$scope module behavioralDecoder $end
$var wire 1 ! address0 $end
$var wire 1 " address1 $end
$var wire 1 # enable $end
$var wire 1 $ out0 $end
$var wire 1 % out1 $end
$var wire 1 & out2 $end
$var wire 1 ' out3 $end
$upscope $end
$scope module testDecoder $end
$var wire 1 ( out0 $end
$var wire 1 ) out1 $end
$var wire 1 * out2 $end
$var wire 1 + out3 $end
$var reg 1 , addr0 $end
$var reg 1 - addr1 $end
$var reg 1 . enable $end
$scope module decoder $end
$var wire 1 / A0andA1 $end
$var wire 1 0 A0andnA1 $end
$var wire 1 1 address0 $end
$var wire 1 2 address1 $end
$var wire 1 3 enable $end
$var wire 1 4 nA0 $end
$var wire 1 5 nA0andA1 $end
$var wire 1 6 nA0andnA1 $end
$var wire 1 7 nA1 $end
$var wire 1 ( out0 $end
$var wire 1 ) out1 $end
$var wire 1 * out2 $end
$var wire 1 + out3 $end
$upscope $end
$upscope $end
$enddefinitions $end
#0
$dumpvars
17
16
05
14
03
02
01
00
0/
0.
0-
0,
0+
0*
0)
0(
x'
x&
x%
x$
z#
z"
z!
$end
#1000000
06
04
10
1,
11
#2000000
07
15
14
00
1-
12
0,
01
#3000000
05
04
1/
1,
11
#4000000
1(
16
17
14
0/
0+
0-
02
0,
01
1.
13
#5000000
0(
06
1)
04
10
1,
11
#6000000
1*
0)
07
15
14
00
1-
12
0,
01
#7000000
0*
05
1+
04
1/
1,
11
